glocalx/.gitignore
glocalx/__init__.py
glocalx/api.py
glocalx/callbacks.py
glocalx/evaluators.py
glocalx/generators.py
glocalx/glocalx.py
glocalx/glocax_probabilistic.py
glocalx/models.py
glocalx/requirements.txt
glocalx/serialization.py
glocalx/data/dummy/dummy_dataset.csv
glocalx/data/dummy/dummy_model.h5
glocalx/data/dummy/dummy_rules.json
glocalx/data/loaders/adult_info.json
glocalx/loaders/lore.py
glocalx-0.0.9.dist-info/METADATA
glocalx-0.0.9.dist-info/WHEEL
glocalx-0.0.9.dist-info/licenses/LICENSE
glocalx-0.0.9.dist-info/RECORD
