Metadata-Version: 2.1
Name: glocalx
Version: 0.0.9
Summary: Generating global explanations from local ones.
Project-URL: Homepage, https://github.com/msetzu/glocalx
Project-URL: Bug Tracker, https://github.com/msetzu/glocalx/issues
Author-email: Mattia Setzu <mattia.setzu@unipi.it>
License-File: LICENSE
Classifier: Development Status :: 2 - Pre-Alpha
Classifier: Intended Audience :: Developers
Classifier: License :: OSI Approved :: GNU General Public License v3 or later (GPLv3+)
Classifier: Operating System :: OS Independent
Classifier: Programming Language :: Python :: 3.8
Requires-Python: <3.11,>=3.8
Requires-Dist: click
Requires-Dist: logzero==1.6.2
Requires-Dist: numpy
Requires-Dist: pandas
Requires-Dist: scikit-learn
Requires-Dist: scipy
